swiftsc/__init__.py
swiftsc/exception.py
swiftsc/client.py
swiftsc/utils.py
swiftsc-0.6.5.dist-info/metadata.json
swiftsc-0.6.5.dist-info/WHEEL
swiftsc-0.6.5.dist-info/RECORD
swiftsc-0.6.5.dist-info/DESCRIPTION.rst
swiftsc-0.6.5.dist-info/METADATA
swiftsc-0.6.5.dist-info/top_level.txt
