Metadata-Version: 2.0
Name: swiftsc
Version: 0.6.5
Summary: Simple client library of OpenStack Swift
Home-page: https://github.com/mkouhei/swiftsc
Author: Kouhei Maeda
Author-email: mkouhei@palmtb.net
License: GNU General Public License version 3
Platform: UNKNOWN
Classifier: Development Status :: 3 - Alpha
Classifier: Intended Audience :: Developers
Classifier: License :: OSI Approved :: GNU General Public License v3 or later (GPLv3+)
Classifier: Programming Language :: Python
Classifier: Programming Language :: Python :: 2.7
Classifier: Programming Language :: Python :: 3.3
Classifier: Programming Language :: Python :: 3.4
Classifier: Programming Language :: Python :: Implementation :: CPython
Classifier: Programming Language :: Python :: Implementation :: PyPy
Classifier: Topic :: Internet
Classifier: Topic :: Internet :: WWW/HTTP
Classifier: Topic :: Software Development :: Libraries :: Python Modules
Classifier: Environment :: OpenStack
Requires-Dist: setuptools
Requires-Dist: requests
Requires-Dist: python-magic
Provides-Extra: reST
Requires-Dist: Sphinx; extra == 'reST'
